{"resourceId":58058,"properties":{"process_id":"NoOpProcess","name":"NoOpProcess","documentation":"","process_author":"","process_version":"","process_namespace":"http://www.activiti.org/processdef","executionlisteners":"","eventlisteners":"","signaldefinitions":"","messagedefinitions":"","executionvariables":"","metadata":""},"stencil":{"id":"BPMNDiagram"},"childShapes":[{"resourceId":"startEvent1","properties":{"overrideid":"","name":"","documentation":"","executionlisteners":"","initiator":"","formkeydefinition":"","formreference":"","fieldstovariables":"","formproperties":""},"stencil":{"id":"StartNoneEvent"},"childShapes":[],"outgoing":[{"resourceId":"sid-9D3717B7-7283-4C93-9AD9-1C3DEA9346A0"}],"bounds":{"lowerRight":{"x":130,"y":193},"upperLeft":{"x":100,"y":163}},"dockers":[]},{"resourceId":"sid-27325F93-0BE4-45E1-8EAD-8A08EAF3E9F5","properties":{"overrideid":"","name":"","documentation":"","executionlisteners":""},"stencil":{"id":"EndNoneEvent"},"childShapes":[],"outgoing":[],"bounds":{"lowerRight":{"x":403,"y":192},"upperLeft":{"x":375,"y":164}},"dockers":[]},{"resourceId":"sid-9D3717B7-7283-4C93-9AD9-1C3DEA9346A0","properties":{"overrideid":"","name":"","documentation":"","conditionsequenceflow":"","executionlisteners":"","defaultflow":"false","showdiamondmarker":false},"stencil":{"id":"SequenceFlow"},"childShapes":[],"outgoing":[{"resourceId":"sid-27325F93-0BE4-45E1-8EAD-8A08EAF3E9F5"}],"bounds":{"lowerRight":{"x":374.703125,"y":178},"upperLeft":{"x":130.421875,"y":178}},"dockers":[{"x":15,"y":15},{"x":24,"y":14}],"target":{"resourceId":"sid-27325F93-0BE4-45E1-8EAD-8A08EAF3E9F5"}}],"bounds":{"lowerRight":{"x":1200,"y":1050},"upperLeft":{"x":0,"y":0}},"stencilset":{"url":"stencilsets/bpmn2.0/bpmn2.0.json","namespace":"http://b3mn.org/stencilset/bpmn2.0#"},"ssextensions":[]}